pyairnow/__init__.py
pyairnow/api.py
pyairnow/conv.py
pyairnow/errors.py
pyairnow/forecast.py
pyairnow/observation.py
pyairnow/py.typed
pyairnow-1.3.1.dist-info/AUTHORS.md
pyairnow-1.3.1.dist-info/LICENSE
pyairnow-1.3.1.dist-info/METADATA
pyairnow-1.3.1.dist-info/WHEEL
pyairnow-1.3.1.dist-info/RECORD
